{"n":20,"team1":"Austria","team2":"Jordan","date":"2026-06-16","stats":{"possession":[53.3,33],"xg":[1.93,0.53],"shots":[10,11],"shots_sub":[4,3],"passes":[587,344],"passes_sub":[499,254],"pass_pct":[85,74],"line_breaks":[112,63],"def_line_breaks":[14,4],"receptions":[132,91],"ball_prog":[35,23],"crosses":[17,15],"pressures":[206,322],"pressures_sub":[44,42],"forced_turnovers":[54,55],"second_balls":[83,85],"distance":[120.4,119.2],"sprint_dist":[6.7,6.7]},"phases_in":{"build_up_unopp":[37,21],"build_up_opp":[15,9],"progression":[17,19],"final_third":[14,19],"long_ball":[3,7],"att_transition":[13,25],"counter":[1,3],"set_piece":[5,10]},"phases_out":{"high_press":[8,4],"mid_press":[3,4],"low_press":[1,0],"high_block":[3,3],"mid_block":[14,22],"low_block":[13,24],"recovery":[7,6],"def_transition":[25,13],"counter_press":[16,10]},"formation":["4-2-3-1","3-4-3"],"players":{"t1":[{"num":1,"name":"Alexander SCHLAGER","phys":[6279,4207.1,1665.2,298.3,71.2,37.3,24,8,30.1],"cross":[0,0,0,0,0,0,0],"lb":{"name":"Alexander SCHLAGER","att":11,"comp":3,"pct":27,"v":[0,0,1,0,4,6,0,0,0,1,1,9,11,0,0]}},{"num":4,"name":"Xaver SCHLAGER","phys":[7334.9,2290.2,3396.8,1195.4,412.7,39.9,101,29,27],"cross":[0,0,0,0,0,0,0],"lb":{"name":"Xaver SCHLAGER","att":13,"comp":13,"pct":100,"v":[0,0,1,0,1,4,0,7,0,8,2,3,13,0,0]}},{"num":5,"name":"Stefan POSCH","phys":[11970.4,3782.7,5002.7,1983.6,752.9,448.5,174,60,32.4],"cross":[0,0,0,0,0,0,0],"lb":{"name":"Stefan POSCH","att":12,"comp":9,"pct":75,"v":[1,0,0,0,1,5,3,2,0,0,4,8,12,0,0]}},{"num":6,"name":"Nicolas SEIWALD","phys":[11721.4,3728.9,5470.2,1772.9,508.3,241.2,160,38,32.7],"cross":[0,1,0,0,0,0,1],"lb":{"name":"Nicolas SEIWALD","att":16,"comp":15,"pct":94,"v":[0,0,0,0,3,5,1,7,0,5,6,5,14,1,1]}},{"num":8,"name":"David ALABA","phys":[6544.3,2325.5,3045.2,781.8,309,82.8,67,21,31.2],"cross":[0,0,0,0,0,0,0],"lb":{"name":"David ALABA","att":15,"comp":10,"pct":67,"v":[0,0,0,0,4,4,1,6,0,1,8,6,15,0,0]}},{"num":9,"name":"Marcel SABITZER","phys":[10942.3,4038.7,4055.3,1715.3,841.1,291.9,139,69,33.6],"cross":[3,2,0,1,0,0,6],"lb":{"name":"Marcel SABITZER","att":14,"comp":10,"pct":71,"v":[0,0,0,0,0,6,4,2,2,2,8,4,10,3,1]}},{"num":14,"name":"Sasa KALAJDZIC","phys":[5537.9,1855.7,2326.7,932,369.3,54.1,76,30,29.5],"cross":[0,0,0,0,0,0,0],"lb":{"name":"Sasa KALAJDZIC","att":2,"comp":1,"pct":50,"v":[0,0,0,0,0,1,1,0,0,1,0,1,2,0,0]}},{"num":15,"name":"Philipp LIENHART","phys":[10672.5,3842,5001.8,1267,434.8,126.9,125,33,32.1],"cross":[0,0,0,0,0,0,0],"lb":{"name":"Philipp LIENHART","att":24,"comp":18,"pct":75,"v":[0,0,0,1,11,5,2,5,0,6,8,10,24,0,0]}},{"num":16,"name":"Phillip MWENE","phys":[7498.4,2131.4,3448.3,1120.2,442.3,356.1,96,41,30.8],"cross":[2,0,0,0,0,1,3],"lb":{"name":"Phillip MWENE","att":5,"comp":5,"pct":100,"v":[0,0,0,0,3,1,0,0,1,0,4,1,5,0,0]}},{"num":18,"name":"Romano SCHMID","phys":[9454.9,3011,3952.2,1660.6,628.8,202.1,142,45,32.5],"cross":[0,0,1,0,0,0,1],"lb":{"name":"Romano SCHMID","att":11,"comp":4,"pct":36,"v":[0,0,0,0,0,5,0,5,1,5,1,5,10,1,0]}},{"num":20,"name":"Konrad LAIMER","phys":[11947.6,3742.5,5489.6,1490.4,804.5,420.6,134,67,34.1],"cross":[0,0,0,1,1,0,2],"lb":{"name":"Konrad LAIMER","att":10,"comp":9,"pct":90,"v":[0,0,0,0,3,2,1,3,1,3,4,3,10,0,0]}},{"num":3,"name":"Kevin DANSO","phys":[4025.2,1602.6,1721.1,489,166.1,46.3,44,14,29.7],"cross":[0,0,0,0,0,0,0],"lb":{"name":"Kevin DANSO","att":7,"comp":4,"pct":57,"v":[0,0,0,0,3,1,0,3,0,3,3,1,7,0,0]}},{"num":7,"name":"Marko ARNAUTOVIC","phys":[5137.4,2456.4,1876.2,569,209.4,26.5,53,19,28.8],"cross":[0,1,0,0,0,0,1],"lb":{"name":"Marko ARNAUTOVIC","att":0,"comp":0,"pct":0,"v":[0,0,0,0,0,0,0,0,0,0,0,0,0,0,0]}},{"num":17,"name":"Carney CHUKWUEMEKA","phys":[4502.7,1571.6,1836.4,706.2,264.8,123.6,63,19,29.4],"cross":[0,0,0,0,0,0,0],"lb":{"name":"Carney CHUKWUEMEKA","att":3,"comp":2,"pct":67,"v":[0,0,0,0,0,1,0,2,0,2,1,0,2,0,1]}},{"num":21,"name":"Patrick WIMMER","phys":[2223.6,696.6,829,392.1,193.4,112.5,31,14,30.3],"cross":[0,0,0,0,0,0,0],"lb":{"name":"Patrick WIMMER","att":3,"comp":3,"pct":100,"v":[0,0,0,0,2,0,1,0,0,1,2,0,2,0,1]}},{"num":24,"name":"Paul WANNER","phys":[4577.1,1507.8,2047.4,741.1,256.2,24.5,67,19,27.9],"cross":[0,0,0,0,0,0,0],"lb":{"name":"Paul WANNER","att":9,"comp":6,"pct":67,"v":[0,0,0,0,1,1,0,7,0,6,2,1,8,0,1]}}],"t2":[{"num":1,"name":"YAZEED ABULAILA","phys":[4736.5,4013.8,694.1,28.6,0,0,4,0,19.8],"cross":[0,0,0,0,0,0,0],"lb":{"name":"YAZEED ABULAILA","att":14,"comp":3,"pct":21,"v":[1,0,1,0,6,5,0,1,0,0,0,14,14,0,0]}},{"num":3,"name":"ABDALLAH NASIB","phys":[8156.8,3157.2,3353.6,1097.8,465.4,82.7,95,33,29.2],"cross":[0,0,0,0,0,0,0],"lb":{"name":"ABDALLAH NASIB","att":13,"comp":9,"pct":69,"v":[0,0,2,0,4,6,0,1,0,4,3,6,13,0,0]}},{"num":5,"name":"YAZAN ALARAB","phys":[9954.9,3970.6,4407.2,1113.2,369.7,94.2,103,27,32.4],"cross":[0,0,0,0,0,0,0],"lb":{"name":"YAZAN ALARAB","att":7,"comp":4,"pct":57,"v":[0,0,1,0,2,3,1,0,0,0,3,4,7,0,0]}},{"num":8,"name":"NOOR ALRAWABDEH","phys":[13030.4,3462.1,5962.6,2663.4,776.4,166,228,55,30.6],"cross":[0,0,0,0,0,0,0],"lb":{"name":"NOOR ALRAWABDEH","att":20,"comp":13,"pct":65,"v":[0,1,1,0,6,6,2,4,0,6,5,9,20,0,0]}},{"num":9,"name":"ALI OLWAN","phys":[12149.4,4192.8,5280.4,1713.2,666.6,296.3,147,53,32.7],"cross":[1,1,0,0,0,0,2],"lb":{"name":"ALI OLWAN","att":5,"comp":2,"pct":40,"v":[0,0,0,0,0,3,2,0,0,3,0,2,5,0,0]}},{"num":10,"name":"MOUSA ALTAMARI","phys":[8690.5,3618.1,3226.5,944.5,525.3,376.1,89,47,34],"cross":[0,1,0,0,0,0,1],"lb":{"name":"MOUSA ALTAMARI","att":2,"comp":2,"pct":100,"v":[0,0,0,1,0,1,0,0,0,2,0,0,1,0,1]}},{"num":11,"name":"ODEH FAKHOURY","phys":[10442.1,3303.5,4412.7,1642.1,778.7,305,158,60,34.5],"cross":[0,0,1,0,0,0,1],"lb":{"name":"ODEH FAKHOURY","att":4,"comp":3,"pct":75,"v":[0,0,0,0,1,1,0,2,0,2,1,1,3,0,1]}},{"num":16,"name":"MOHAMMAD ABUALNADI","phys":[8416,2401.1,4107.4,1246.2,385,276.3,115,31,31.2],"cross":[0,0,0,0,0,0,0],"lb":{"name":"MOHAMMAD ABUALNADI","att":12,"comp":9,"pct":75,"v":[1,0,0,0,5,3,0,3,0,2,5,5,12,0,0]}},{"num":20,"name":"MOHANNAD ABUTAHA","phys":[11617.9,4009,4609.2,1813.9,974.5,211.3,174,70,31.2],"cross":[0,4,0,0,0,1,5],"lb":{"name":"MOHANNAD ABUTAHA","att":9,"comp":5,"pct":56,"v":[1,0,1,0,0,4,0,1,2,3,3,3,7,1,1]}},{"num":21,"name":"NIZAR ALRASHDAN","phys":[11703.6,3586.3,5480.2,1905.5,598.1,133.6,167,48,29.6],"cross":[0,0,0,0,0,0,0],"lb":{"name":"NIZAR ALRASHDAN","att":7,"comp":5,"pct":71,"v":[0,0,0,0,1,3,0,3,0,1,0,6,7,0,0]}},{"num":23,"name":"EHSAN HADDAD","phys":[9086.5,3382,3547.8,1382,579.2,195.5,115,48,29.9],"cross":[2,1,0,0,0,1,4],"lb":{"name":"EHSAN HADDAD","att":7,"comp":1,"pct":14,"v":[0,1,0,0,0,2,1,2,1,0,3,4,6,1,0]}},{"num":13,"name":"MAHMOUD ALMARDI","phys":[2632.6,782.4,1169.3,542.6,107.5,30.9,45,8,27.5],"cross":[1,0,0,0,0,0,1],"lb":{"name":"MAHMOUD ALMARDI","att":3,"comp":2,"pct":67,"v":[0,0,0,0,0,2,0,1,0,0,1,2,2,1,0]}},{"num":17,"name":"SALEEM OBAID","phys":[2818.7,921.6,1422.3,322.1,141.3,11.3,25,10,26.7],"cross":[0,0,0,0,0,0,0],"lb":{"name":"SALEEM OBAID","att":5,"comp":2,"pct":40,"v":[0,0,0,0,2,3,0,0,0,1,1,3,5,0,0]}},{"num":19,"name":"SAED ALROSAN","phys":[2425.1,733.8,1163.8,371.7,132.1,23.7,36,12,31],"cross":[0,0,0,0,0,0,0],"lb":{"name":"SAED ALROSAN","att":2,"comp":2,"pct":100,"v":[0,0,0,0,0,1,0,1,0,0,1,1,2,0,0]}},{"num":24,"name":"ALI AZAIZEH","phys":[1740.7,513.7,777.9,302.3,94.7,52.2,23,8,30],"cross":[0,0,0,0,0,0,0],"lb":{"name":"ALI AZAIZEH","att":1,"comp":1,"pct":100,"v":[0,0,0,0,0,0,0,1,0,0,1,0,0,0,1]}},{"num":25,"name":"MOHAMMAD ALDAOUD","phys":[1620.2,479.3,674.9,356.9,100.6,8.5,28,7,25.9],"cross":[0,0,0,0,0,0,0],"lb":{"name":"MOHAMMAD ALDAOUD","att":2,"comp":0,"pct":0,"v":[0,0,0,0,0,1,0,0,1,0,1,1,2,0,0]}}]},"physical":{"t1":{"sprints":526,"hsr":1496,"top_speed":34.1,"top_player":"Konrad LAIMER"},"t2":{"sprints":517,"hsr":1552,"top_speed":34.5,"top_player":"ODEH FAKHOURY"}}}