{"n":66,"team1":"Uruguay","team2":"Spain","date":"2026-06-26","stats":{"possession":[33.4,57.1],"xg":[0.22,1.12],"shots":[5,6],"shots_sub":[1,1],"passes":[305,637],"passes_sub":[241,570],"pass_pct":[79,89],"line_breaks":[68,134],"def_line_breaks":[15,10],"receptions":[94,89],"ball_prog":[24,37],"crosses":[18,15],"pressures":[390,215],"pressures_sub":[64,35],"forced_turnovers":[53,49],"second_balls":[67,65],"distance":[113.8,111.2],"sprint_dist":[6.5,5.1]},"phases_in":{"build_up_unopp":[28,40],"build_up_opp":[10,20],"progression":[15,14],"final_third":[16,8],"long_ball":[7,2],"att_transition":[19,10],"counter":[2,1],"set_piece":[7,4]},"phases_out":{"high_press":[8,6],"mid_press":[7,4],"low_press":[1,0],"high_block":[7,5],"mid_block":[21,17],"low_block":[22,17],"recovery":[3,6],"def_transition":[10,19],"counter_press":[8,12]},"formation":["4-1-2-3","4-1-2-3"],"players":{"t1":[{"num":23,"name":"Fernando MUSLERA","phys":[2038.4,1722.8,285.3,30.3,0,0,2,0,18.7],"cross":[0,0,0,0,0,0,0],"lb":{"name":"Fernando MUSLERA","att":10,"comp":4,"pct":40,"v":[0,0,0,0,2,6,1,1,0,0,0,10,10,0,0]}},{"num":3,"name":"Sebastian CACERES","phys":[10228.3,4177.1,4109.5,1364.3,412.2,165.2,119,34,33],"cross":[0,0,0,0,0,0,0],"lb":{"name":"Sebastian CACERES","att":10,"comp":7,"pct":70,"v":[0,0,0,0,2,4,0,4,0,1,3,6,9,0,1]}},{"num":5,"name":"Manuel UGARTE","phys":[4667.1,1731.6,1981.7,666.6,241.2,46,60,20,29.4],"cross":[0,0,0,0,0,0,0],"lb":{"name":"Manuel UGARTE","att":6,"comp":2,"pct":33,"v":[0,0,0,0,0,3,2,1,0,3,0,3,6,0,0]}},{"num":6,"name":"Rodrigo BENTANCUR","phys":[11211,4594.7,4308.1,1447.1,636.1,225,127,54,32.6],"cross":[0,2,0,0,0,0,2],"lb":{"name":"Rodrigo BENTANCUR","att":9,"comp":7,"pct":78,"v":[0,0,0,0,1,4,0,3,1,5,2,2,8,0,1]}},{"num":8,"name":"Federico VALVERDE","phys":[6793.8,2126.7,3154.7,853.1,451.5,207.9,77,37,34.9],"cross":[0,0,0,0,0,2,2],"lb":{"name":"Federico VALVERDE","att":4,"comp":3,"pct":75,"v":[0,0,0,0,1,2,1,0,0,0,4,0,4,0,0]}},{"num":9,"name":"Darwin NUNEZ","phys":[11210.2,4409.9,4152,1495.8,731.2,421.3,124,58,34.8],"cross":[0,1,0,0,1,0,2],"lb":{"name":"Darwin NUNEZ","att":3,"comp":2,"pct":67,"v":[0,0,1,0,0,0,0,1,1,0,2,1,3,0,0]}},{"num":13,"name":"Guillermo VARELA","phys":[10731.6,4108.2,4483.9,1359.3,565.7,214.5,122,40,32.8],"cross":[0,1,0,0,0,0,1],"lb":{"name":"Guillermo VARELA","att":12,"comp":9,"pct":75,"v":[0,0,0,1,2,5,0,3,1,1,6,5,12,0,0]}},{"num":14,"name":"Agustin CANOBBIO","phys":[11228.2,3769.8,4479.6,1625.7,780.8,572.2,146,68,33.4],"cross":[0,1,0,0,0,1,2],"lb":{"name":"Agustin CANOBBIO","att":3,"comp":2,"pct":67,"v":[0,0,0,0,1,0,2,0,0,1,2,0,1,1,1]}},{"num":16,"name":"Mathias OLIVERA","phys":[11482.8,4135.9,4802.5,1902.5,551.5,90.4,151,41,28.4],"cross":[0,0,0,0,0,2,2],"lb":{"name":"Mathias OLIVERA","att":15,"comp":10,"pct":67,"v":[0,0,0,0,4,3,2,5,1,8,4,3,14,1,0]}},{"num":20,"name":"Maxi ARAUJO","phys":[10319.8,3925.2,3978.2,1422.7,707.7,285.9,119,48,31.5],"cross":[0,0,1,0,0,0,1],"lb":{"name":"Maxi ARAUJO","att":10,"comp":7,"pct":70,"v":[0,0,0,0,0,2,2,5,1,1,5,4,7,2,1]}},{"num":25,"name":"Juan Manuel SANABRIA","phys":[7893,3111.4,2925.2,1114.2,495.8,246.4,93,36,32],"cross":[0,2,0,0,0,0,2],"lb":{"name":"Juan Manuel SANABRIA","att":4,"comp":4,"pct":100,"v":[0,0,0,0,0,3,0,1,0,1,1,2,4,0,0]}},{"num":1,"name":"Sergio ROCHET","phys":[3079.4,2053.9,896.5,85.2,27.3,16.5,6,3,28.2],"cross":[0,0,0,0,0,0,0],"lb":{"name":"Sergio ROCHET","att":12,"comp":4,"pct":33,"v":[0,0,0,0,2,6,3,1,0,1,0,11,12,0,0]}},{"num":7,"name":"Nicolas DE LA CRUZ","phys":[6185.9,2048.9,2559.1,1004.4,445.2,128.3,90,29,29.6],"cross":[0,0,0,0,0,0,0],"lb":{"name":"Nicolas DE LA CRUZ","att":7,"comp":4,"pct":57,"v":[0,0,0,0,1,2,4,0,0,5,0,2,7,0,0]}},{"num":18,"name":"Brian RODRIGUEZ","phys":[2790.6,1094.6,1120.7,354.1,184.5,36.7,34,14,29.2],"cross":[0,0,0,0,0,0,0],"lb":{"name":"Brian RODRIGUEZ","att":2,"comp":2,"pct":100,"v":[0,0,0,0,0,0,2,0,0,0,1,1,1,0,1]}},{"num":21,"name":"Federico VINAS","phys":[3897.5,1863,1109.4,559.3,274.5,91.3,38,21,29.1],"cross":[0,0,0,0,0,0,0],"lb":{"name":"Federico VINAS","att":1,"comp":1,"pct":100,"v":[0,0,0,0,0,1,0,0,0,0,0,1,1,0,0]}}],"t2":[{"num":23,"name":"Unai SIMON","phys":[5824.1,4350.7,1116.7,259.9,83.8,13,27,5,25.7],"cross":[0,0,0,0,0,0,0],"lb":{"name":"Unai SIMON","att":13,"comp":8,"pct":62,"v":[0,3,1,0,5,2,0,2,0,3,0,10,13,0,0]}},{"num":5,"name":"Marcos LLORENTE","phys":[10177.4,4320.1,3906.9,1143.1,525.7,281.4,101,42,31.8],"cross":[0,2,0,0,0,0,2],"lb":{"name":"Marcos LLORENTE","att":16,"comp":13,"pct":81,"v":[1,0,0,0,9,1,0,4,1,2,11,3,15,0,1]}},{"num":6,"name":"Mikel MERINO","phys":[7811.2,2387.8,3363.6,1620.4,410.3,29,137,30,26.9],"cross":[0,0,0,0,0,0,0],"lb":{"name":"Mikel MERINO","att":10,"comp":10,"pct":100,"v":[0,0,0,0,1,4,0,4,1,6,3,1,10,0,0]}},{"num":14,"name":"Aymeric LAPORTE","phys":[9482.1,4404.1,3682.8,982,355.6,57.6,85,25,28.3],"cross":[0,0,0,0,0,0,0],"lb":{"name":"Aymeric LAPORTE","att":27,"comp":22,"pct":81,"v":[2,0,0,0,13,3,3,6,0,11,8,8,25,0,2]}},{"num":15,"name":"Alex BAENA","phys":[7684.1,3141.7,2909.1,1048.2,382.5,202.5,90,30,33.5],"cross":[1,1,0,0,0,0,2],"lb":{"name":"Alex BAENA","att":7,"comp":5,"pct":71,"v":[0,0,1,0,0,2,1,1,2,3,2,2,6,1,0]}},{"num":16,"name":"RODRI","phys":[11840.7,3903.1,5227.4,2013.9,597.3,98.9,168,37,27.9],"cross":[0,0,0,0,0,0,0],"lb":{"name":"RODRI","att":18,"comp":17,"pct":94,"v":[0,1,0,0,8,1,0,7,1,11,6,1,17,0,1]}},{"num":19,"name":"Lamine YAMAL","phys":[7496.2,3679.9,2517.1,804.4,418,76.8,71,34,31.4],"cross":[1,0,0,0,1,1,3],"lb":{"name":"Lamine YAMAL","att":4,"comp":2,"pct":50,"v":[0,0,0,0,0,0,1,1,2,1,2,1,1,1,2]}},{"num":20,"name":"PEDRI","phys":[7637.8,2411.5,3486.1,1301.1,394.2,45,111,30,27],"cross":[0,1,0,0,0,0,1],"lb":{"name":"PEDRI","att":10,"comp":8,"pct":80,"v":[0,0,0,0,0,0,0,10,0,4,6,0,10,0,0]}},{"num":21,"name":"Mikel OYARZABAL","phys":[7459.1,3423.3,2438.2,929.8,472.1,195.8,77,41,30.1],"cross":[0,0,0,0,0,1,1],"lb":{"name":"Mikel OYARZABAL","att":5,"comp":3,"pct":60,"v":[0,0,0,0,0,3,0,1,1,1,2,2,3,1,1]}},{"num":22,"name":"Pau CUBARSI","phys":[10275.9,4309.2,4255.5,1198.2,354.6,158.4,108,29,31.3],"cross":[0,0,0,0,0,0,0],"lb":{"name":"Pau CUBARSI","att":21,"comp":21,"pct":100,"v":[1,0,0,1,9,3,0,7,0,10,9,2,18,0,3]}},{"num":24,"name":"Marc CUCURELLA","phys":[10114.9,4397.6,3971.8,1183.5,343,219.1,104,32,31.1],"cross":[0,0,0,0,0,0,0],"lb":{"name":"Marc CUCURELLA","att":12,"comp":8,"pct":67,"v":[0,0,1,0,5,3,0,2,1,4,4,4,12,0,0]}},{"num":7,"name":"Ferran TORRES","phys":[2150,995.8,763.3,222.6,109.3,59,22,11,30.6],"cross":[0,0,0,0,0,0,0],"lb":{"name":"Ferran TORRES","att":1,"comp":1,"pct":100,"v":[0,0,0,0,0,0,1,0,0,1,0,0,0,0,1]}},{"num":8,"name":"Fabian RUIZ","phys":[4086.2,1552.3,1633.7,714.3,126.7,59.1,55,12,30.1],"cross":[0,0,0,0,0,0,0],"lb":{"name":"Fabian RUIZ","att":7,"comp":6,"pct":86,"v":[0,0,0,0,3,3,0,1,0,2,3,2,6,0,1]}},{"num":10,"name":"Dani OLMO","phys":[3833.6,1274.2,1705.9,624.4,172.5,56.5,56,17,28.8],"cross":[0,0,0,0,0,0,0],"lb":{"name":"Dani OLMO","att":11,"comp":9,"pct":82,"v":[0,0,0,0,1,8,0,1,1,6,3,2,9,0,2]}},{"num":11,"name":"Yeremy PINO","phys":[3173.1,1138.8,1350.3,380.5,219.5,84,34,14,30.7],"cross":[0,0,0,0,0,0,0],"lb":{"name":"Yeremy PINO","att":1,"comp":1,"pct":100,"v":[0,0,0,0,0,1,0,0,0,0,1,0,1,0,0]}},{"num":17,"name":"Nico WILLIAMS","phys":[2121.9,814.4,933.7,184.5,128.1,61.1,16,12,31.5],"cross":[0,0,0,0,0,0,0],"lb":{"name":"Nico WILLIAMS","att":1,"comp":0,"pct":0,"v":[0,0,0,0,0,1,0,0,0,1,0,0,1,0,0]}}]},"physical":{"t1":{"sprints":503,"hsr":1308,"top_speed":34.9,"top_player":"Federico VALVERDE"},"t2":{"sprints":401,"hsr":1262,"top_speed":33.5,"top_player":"Alex BAENA"}}}